MANIFEST.in
README.rst
pyvenv.cfg
setup.cfg
setup.py
docs/CREDITS.txt
docs/HISTORY.rst
docs/LICENSE.txt
src/roughrider/__init__.py
src/roughrider.storage.egg-info/PKG-INFO
src/roughrider.storage.egg-info/SOURCES.txt
src/roughrider.storage.egg-info/dependency_links.txt
src/roughrider.storage.egg-info/not-zip-safe
src/roughrider.storage.egg-info/requires.txt
src/roughrider.storage.egg-info/top_level.txt
src/roughrider/storage/__init__.py
src/roughrider/storage/bushy.py
src/roughrider/storage/flat.py
src/roughrider/storage/fs.py
src/roughrider/storage/meta.py
src/roughrider/storage/pyfs.py
tests/conftest.py
tests/test_bushy.py
tests/test_center.py
tests/test_flat.py
tests/test_pyfs.py