Metadata-Version: 2.4
Name: roughrider.storage
Version: 0.2.1
Summary: File storage utility implementation
Home-page: http://pypi.python.org/pypi/roughrider.storage
Author: Souheil Chelfouh
Author-email: trollfot@gmail.com
Maintainer: Souheil Chelfouh
Maintainer-email: trollfot@gmail.com
License: ZPL
Classifier: Environment :: Web Environment
Classifier: Intended Audience :: Developers
Classifier: License :: OSI Approved :: Zope Public License
Classifier: Programming Language :: Python :: 3.10
Classifier: Programming Language :: Python :: 3.11
Classifier: Programming Language :: Python :: 3.12
Classifier: Programming Language :: Python :: 3.13
Requires-Python: >=3.10
Requires-Dist: nanoid
Provides-Extra: test
Requires-Dist: pytest; extra == "test"
Dynamic: provides-extra
Dynamic: requires-dist
